batchgenerators/__init__.py
batchgenerators/augmentations/__init__.py
batchgenerators/augmentations/color_augmentations.py
batchgenerators/augmentations/crop_and_pad_augmentations.py
batchgenerators/augmentations/noise_augmentations.py
batchgenerators/augmentations/normalizations.py
batchgenerators/augmentations/resample_augmentations.py
batchgenerators/augmentations/spatial_transformations.py
batchgenerators/augmentations/utils.py
batchgenerators/dataloading/__init__.py
batchgenerators/dataloading/data_loader.py
batchgenerators/dataloading/dataset.py
batchgenerators/dataloading/multi_threaded_augmenter.py
batchgenerators/dataloading/single_threaded_augmenter.py
batchgenerators/datasets/__init__.py
batchgenerators/datasets/cifar.py
batchgenerators/examples/__init__.py
batchgenerators/examples/cifar10.py
batchgenerators/examples/multithreaded_dataloading.py
batchgenerators/examples/brats2017/__init__.py
batchgenerators/examples/brats2017/brats2017_dataloader_2D.py
batchgenerators/examples/brats2017/brats2017_dataloader_3D.py
batchgenerators/examples/brats2017/brats2017_preprocessing.py
batchgenerators/examples/brats2017/config.py
batchgenerators/transforms/__init__.py
batchgenerators/transforms/abstract_transforms.py
batchgenerators/transforms/channel_selection_transforms.py
batchgenerators/transforms/color_transforms.py
batchgenerators/transforms/crop_and_pad_transforms.py
batchgenerators/transforms/noise_transforms.py
batchgenerators/transforms/resample_transforms.py
batchgenerators/transforms/sample_normalization_transforms.py
batchgenerators/transforms/spatial_transforms.py
batchgenerators/transforms/utility_transforms.py
batchgenerators/utilities/__init__.py
batchgenerators/utilities/data_splitting.py
batchgenerators/utilities/file_and_folder_operations.py
batchgenerators-0.21.dist-info/LICENSE
batchgenerators-0.21.dist-info/METADATA
batchgenerators-0.21.dist-info/WHEEL
batchgenerators-0.21.dist-info/top_level.txt
batchgenerators-0.21.dist-info/RECORD
