Metadata-Version: 2.1
Name: batchgenerators
Version: 0.21
Summary: Data augmentation toolkit
Home-page: https://github.com/MIC-DKFZ/batchgenerators
Author: Division of Medical Image Computing, German Cancer Research Center
Author-email: f.isensee@dkfz-heidelberg.de
License: Apache License Version 2.0, January 2004
Download-URL: https://github.com/MIC-DKFZ/batchgenerators/archive/v0.19.5.tar.gz
Keywords: deep learning,image segmentation,image classification,medical image analysis,medical image segmentation,data augmentation
Platform: UNKNOWN
Requires-Dist: pillow (>=7.1.2)
Requires-Dist: numpy (>=1.10.2)
Requires-Dist: scipy
Requires-Dist: scikit-image
Requires-Dist: scikit-learn
Requires-Dist: future
Requires-Dist: unittest2
Requires-Dist: threadpoolctl
